pytest_resource_path/__init__.py
pytest_resource_path/absolute_path_factory.py
pytest_resource_path/exceptions.py
pytest_resource_path/path_factory.py
pytest_resource_path/path_to_resource_factory.py
pytest_resource_path/py.typed
pytest_resource_path/pytest_backward_compatibility.py
pytest_resource_path/pytest_resource_path.py
pytest_resource_path-1.4.1.dist-info/licenses/LICENSE
pytest_resource_path-1.4.1.dist-info/METADATA
pytest_resource_path-1.4.1.dist-info/WHEEL
pytest_resource_path-1.4.1.dist-info/entry_points.txt
pytest_resource_path-1.4.1.dist-info/top_level.txt
pytest_resource_path-1.4.1.dist-info/RECORD
